AUTHORS.rst
CONTRIBUTING.rst
HISTORY.rst
LICENSE
MANIFEST.in
README.rst
setup.cfg
setup.py
docs/Makefile
docs/authors.rst
docs/conf.py
docs/contributing.rst
docs/history.rst
docs/index.rst
docs/installation.rst
docs/lines_table.rst
docs/make.bat
docs/modules.rst
docs/readme.rst
docs/usage.rst
docs/_build/html/_static/ajax-loader.gif
docs/_build/html/_static/comment-bright.png
docs/_build/html/_static/comment-close.png
docs/_build/html/_static/comment.png
docs/_build/html/_static/down-pressed.png
docs/_build/html/_static/down.png
docs/_build/html/_static/file.png
docs/_build/html/_static/minus.png
docs/_build/html/_static/plus.png
docs/_build/html/_static/up-pressed.png
docs/_build/html/_static/up.png
lines_table/__init__.py
lines_table/cli.py
lines_table/lines_table.py
lines_table.egg-info/PKG-INFO
lines_table.egg-info/SOURCES.txt
lines_table.egg-info/dependency_links.txt
lines_table.egg-info/entry_points.txt
lines_table.egg-info/not-zip-safe
lines_table.egg-info/requires.txt
lines_table.egg-info/top_level.txt
tests/test_lines_table.py