Metadata-Version: 1.1
Name: lines-table
Version: 0.1.0
Summary: A tool for converting traditional shipwrights offset tables for defining boat hulls into electronic forms
Home-page: https://github.com/bobm123/lines_table
Author: Robert Marchese
Author-email: bobm123@gmail.com
License: MIT license
Keywords: lines_table
Platform: UNKNOWN
Classifier: Development Status :: 2 - Pre-Alpha
Classifier: Intended Audience :: Developers
Classifier: License :: OSI Approved :: MIT License
Classifier: Natural Language :: English
Classifier: Programming Language :: Python :: 2
Classifier: Programming Language :: Python :: 2.7
Classifier: Programming Language :: Python :: 3
Classifier: Programming Language :: Python :: 3.4
Classifier: Programming Language :: Python :: 3.5
Classifier: Programming Language :: Python :: 3.6
